k_llms/__init__.py
k_llms/client.py
k_llms/resources/__init__.py
k_llms/resources/completions/__init__.py
k_llms/resources/completions/completions.py
k_llms/resources/responses/__init__.py
k_llms/resources/responses/responses.py
k_llms/types/__init__.py
k_llms/types/completions.py
k_llms/types/parsed.py
k_llms/types/responses.py
k_llms/utils/__init__.py
k_llms/utils/consensus_utils.py
k_llms/utils/consolidation.py
k_llms/utils/majority_sorting.py
k_llms-0.0.52.dist-info/METADATA
k_llms-0.0.52.dist-info/WHEEL
k_llms-0.0.52.dist-info/top_level.txt
k_llms-0.0.52.dist-info/RECORD
