Metadata-Version: 2.1
Name: k-llms
Version: 0.0.52
Summary: Retab official python library
Home-page: https://github.com/Retab-dev/retab
Author: Retab
Author-email: contact@retab.com
Project-URL: Team website, https://retab.com
Classifier: Programming Language :: Python :: 3
Classifier: License :: OSI Approved :: MIT License
Classifier: Operating System :: POSIX :: Linux
Classifier: Operating System :: MacOS
Classifier: Intended Audience :: Science/Research
Requires-Python: >=3.6
Requires-Dist: numpy
Requires-Dist: cachetools
Requires-Dist: python-Levenshtein
Requires-Dist: openai
Requires-Dist: pydantic
Requires-Dist: scipy
Requires-Dist: retab
Requires-Dist: Unidecode
